brix_term-0.1.3.dist-info/licenses/LICENSE
brixterm/__init__.py
brixterm/command_executor.py
brixterm/command_history.py
brixterm/console_context.py
brixterm/console_printer.py
brixterm/constants.py
brixterm/main.py
brixterm/terminal_app.py
brixterm/ai/__init__.py
brixterm/ai/chatbot.py
brixterm/ai/code_generator.py
brixterm/ai/smart_terminal.py
brixterm/ai/tools/__init__.py
brixterm/ai/tools/paste_to_clipboard.py
brix_term-0.1.3.dist-info/METADATA
brix_term-0.1.3.dist-info/WHEEL
brix_term-0.1.3.dist-info/entry_points.txt
brix_term-0.1.3.dist-info/top_level.txt
brix_term-0.1.3.dist-info/RECORD
