Metadata-Version: 2.4
Name: brix-term
Version: 0.1.3
Summary: GPT powered terminal for Python developers.
Author-email: Matej Kvassay <matejkvassay5@gmail.com>
Project-URL: Homepage, https://github.com/matejkvassay/BrixTerm
Project-URL: Repository, https://github.com/matejkvassay/BrixTerm
Project-URL: Issues, https://github.com/matejkvassay/BrixTerm/issues
Project-URL: Documentation, https://github.com/matejkvassay/BrixTerm#readme
Keywords: LLM,agent,AI,terminal,application,chatbot,llmbrix,llmbricks
Classifier: Programming Language :: Python :: 3
Classifier: Programming Language :: Python :: 3.11
Classifier: License :: OSI Approved :: Apache Software License
Classifier: Operating System :: OS Independent
Classifier: Development Status :: 3 - Alpha
Classifier: Intended Audience :: Developers
Classifier: Topic :: Software Development :: Libraries
Requires-Python: >=3.11
License-File: LICENSE
Requires-Dist: llmbrix>=0.1.3
Requires-Dist: rich
Requires-Dist: pyperclip
Provides-Extra: dev
Requires-Dist: pytest; extra == "dev"
Requires-Dist: pre-commit; extra == "dev"
Requires-Dist: build; extra == "dev"
Requires-Dist: twine; extra == "dev"
Dynamic: license-file
